autodistill_altclip/__init__.py
autodistill_altclip/altclip_model.py
autodistill_altclip-0.1.2.dist-info/LICENSE
autodistill_altclip-0.1.2.dist-info/METADATA
autodistill_altclip-0.1.2.dist-info/WHEEL
autodistill_altclip-0.1.2.dist-info/top_level.txt
autodistill_altclip-0.1.2.dist-info/RECORD
